memory.v
module memory_64x16 (
    input              writeEnable,
    input  [5:0]       addr,    // 6-bit for 64 rows
    input  [15:0]      din,
    output [15:0]      dout
);

    // 64 rows × 16 bits
    reg [15:0] mem [0:63];

    // Asynchronous read
    assign dout = mem[addr];

    // Synchronous write
    always @(*) begin
        if (writeEnable)
            mem[addr] <= din;
    end

    // Load memory content from file at simulation start
    initial begin
        $readmemb("mem_init.bin", mem);
        // or: $readmemb("mem_init.bin", mem); // for binary file
    end

endmodule

tb_memory.v
module tb_mem;

    reg we;
    reg [5:0] addr;
    reg [15:0] din;
    wire [15:0] dout;

    memory_64x16 dut ( .writeEnable(we), .addr(addr), .din(din), .dout(dout));

    initial begin
        $dumpfile("wave.vcd");
        $dumpvars(0, tb_mem);
        // wait for memory to load
        #1;        
        // Read first few locations (async)
        addr = 0; #1 $display("mem[0] = %h", dout);
        addr = 1; #1 $display("mem[1] = %h", dout);
        addr = 2; #1 $display("mem[2] = %h", dout);

        // Write example
        addr = 3; din = 16'h1234; we = 1; #1
        addr = 4; din = 16'h4321; we = 1; #1
        addr = 5; din = 16'h70F0; we = 1; #1
        
        we = 0;
        // Read written value
        addr = 3;
        #1 $display("mem[3] after write = %h", dout);
        addr = 4;
        #1 $display("mem[3] after write = %h", dout);
        addr = 5;
        #1 $display("mem[3] after write = %h", dout);

        #20 $finish;
    end

endmodule

wave.vcd
$date
	Wed Nov 19 23:31:58 2025
$end
$version
	Icarus Verilog
$end
$timescale
	1s
$end
$scope module tb_mem $end
$var wire 16 ! dout [15:0] $end
$var reg 6 " addr [5:0] $end
$var reg 16 # din [15:0] $end
$var reg 1 $ we $end
$scope module dut $end
$var wire 6 % addr [5:0] $end
$var wire 16 & din [15:0] $end
$var wire 16 ' dout [15:0] $end
$var wire 1 $ writeEnable $end
$upscope $end
$upscope $end
$enddefinitions $end
$comment Show the parameter values. $end
$dumpall
$end
#0
$dumpvars
bx '
bx &
bx %
x$
bx #
bx "
bx !
$end
#1
b1 !
b1 '
b0 "
b0 %
#2
b10 !
b10 '
b1 "
b1 %
#3
b11111111 !
b11111111 '
b10 "
b10 %
#4
1$
b1001000110100 #
b1001000110100 &
b1001000110100 !
b1001000110100 '
b11 "
b11 %
#5
b100001100100001 #
b100001100100001 &
b100001100100001 !
b100001100100001 '
b100 "
b100 %
#6
b111000011110000 #
b111000011110000 &
b111000011110000 !
b111000011110000 '
b101 "
b101 %
#7
b1001000110100 !
b1001000110100 '
b11 "
b11 %
0$
#8
b100001100100001 !
b100001100100001 '
b100 "
b100 %
#9
b111000011110000 !
b111000011110000 '
b101 "
b101 %
